esis/__init__.py
esis/esis.ipynb
esis/data/.gitignore
esis/data/__init__.py
esis/data/level_0.py
esis/data/level_1.py
esis/data/level_2.py
esis/data/level_3.py
esis/data/level_4.py
esis/data/nsroc.py
esis/data/test_level_0.py
esis/data/test_level_1.py
esis/data/test_level_3.py
esis/data/test_level_4.py
esis/data/inversion/__init__.py
esis/data/inversion/cnn.py
esis/data/inversion/mart/__init__.py
esis/data/inversion/mart/antialias.py
esis/data/inversion/mart/blue_or_red.ipynb
esis/data/inversion/mart/forward.py
esis/data/inversion/mart/helper.py
esis/data/inversion/mart/lgof_mart.py
esis/data/inversion/mart/mart.py
esis/data/inversion/mart/result.py
esis/data/inversion/mart/simple_mart.py
esis/data/inversion/mart/stats.py
esis/data/inversion/mart/test_antialias.py
esis/data/inversion/mart/test_mart.ipynb
esis/data/inversion/moses_mart/__init__.py
esis/data/inversion/moses_mart/sampling_issue/IRIS test.ipynb
esis/data/inversion/moses_mart/sampling_issue/Normalization Test.ipynb
esis/data/inversion/moses_mart/sampling_issue/SimplePlaid.ipynb
esis/data/inversion/moses_mart/sampling_issue/__init__.py
esis/data/inversion/moses_mart/sampling_issue/ee-1.png
esis/data/inversion/moses_mart/sampling_issue/ee-2.png
esis/data/inversion/moses_mart/sampling_issue/ee-3.png
esis/data/inversion/moses_mart/sampling_issue/moses.py
esis/flight/.gitignore
esis/flight/__init__.py
esis/flight/__init__test.py
esis/flight/aia_to_fits.py
esis/flight/generate_level3_pickle.py
esis/flight/l3_events.py
esis/flight/mart_invert_level3.py
esis/flight/optics.py
esis/flight/images/ESIS1_00096.fit.gz
esis/flight/images/ESIS1_00097.fit.gz
esis/flight/images/ESIS1_00098.fit.gz
esis/flight/images/ESIS1_00099.fit.gz
esis/flight/images/ESIS1_00100.fit.gz
esis/flight/images/ESIS1_00101.fit.gz
esis/flight/images/ESIS1_00102.fit.gz
esis/flight/images/ESIS1_00103.fit.gz
esis/flight/images/ESIS1_00104.fit.gz
esis/flight/images/ESIS1_00105.fit.gz
esis/flight/images/ESIS1_00106.fit.gz
euv_snapshot_imaging_spectrograph-0.1.1.dist-info/METADATA
euv_snapshot_imaging_spectrograph-0.1.1.dist-info/WHEEL
euv_snapshot_imaging_spectrograph-0.1.1.dist-info/top_level.txt
euv_snapshot_imaging_spectrograph-0.1.1.dist-info/RECORD
